simplebloom/__init__.py
simplebloom/_cbloom.cpython-39-x86_64-linux-gnu.so
simplebloom/_pybloom.py
simplebloom/bloom.py
simplebloom-1.1.0.dist-info/METADATA
simplebloom-1.1.0.dist-info/WHEEL
simplebloom-1.1.0.dist-info/top_level.txt
simplebloom-1.1.0.dist-info/RECORD
simplebloom-1.1.0.dist-info/licenses/LICENSE
