Metadata-Version: 2.4
Name: simplebloom
Version: 1.1.0
Summary: A dumb but fast bloom filter.
Author-email: Joachim Folz <joachim.folz@dfki.de>
License-Expression: MIT
Project-URL: Documentation, https://github.com/jfolz/simplebloom/blob/main/README.rst
Project-URL: Source, https://github.com/jfolz/simplebloom
Project-URL: Tracker, https://github.com/jfolz/simplebloom/issues
Keywords: bloom,filter,bloomfilter
Classifier: Development Status :: 5 - Production/Stable
Classifier: Intended Audience :: Science/Research
Requires-Python: >=3.9
License-File: LICENSE
Dynamic: license-file
